laraflask/__init__.py
laraflask/core.py
laraflask_core-1.0.1.dist-info/licenses/LICENSE
laraflask_core-1.0.1.dist-info/METADATA
laraflask_core-1.0.1.dist-info/WHEEL
laraflask_core-1.0.1.dist-info/top_level.txt
laraflask_core-1.0.1.dist-info/RECORD
