Metadata-Version: 2.4
Name: laraflask-core
Version: 1.0.1
Summary: Laraflask ecosystem init root.
Home-page: https://github.com/riodevnet/laraflask
Author: Rio Agung Purnomo
Author-email: laraflask@ryucode.com
Classifier: Development Status :: 5 - Production/Stable
Classifier: Programming Language :: Python :: 3
Classifier: Framework :: Flask
Classifier: License :: OSI Approved :: MIT License
Classifier: Operating System :: OS Independent
Requires-Python: >=3.7
License-File: LICENSE
Requires-Dist: Flask
Requires-Dist: MarkupSafe
Requires-Dist: python-dotenv
Requires-Dist: click
Dynamic: author
Dynamic: author-email
Dynamic: classifier
Dynamic: description
Dynamic: description-content-type
Dynamic: home-page
Dynamic: license-file
Dynamic: requires-dist
Dynamic: requires-python
Dynamic: summary
